nebtasks/__init__.py
nebtasks/task_extensions.py
nebtasks/tasks/__init__.py
nebtasks/tasks/broken_imgs.py
nebtasks/tasks/empty_elements.py
nebtasks/tasks/shortlink_report.py
neb_tasks-0.4.0.dist-info/LICENSE.txt
neb_tasks-0.4.0.dist-info/METADATA
neb_tasks-0.4.0.dist-info/WHEEL
neb_tasks-0.4.0.dist-info/entry_points.txt
neb_tasks-0.4.0.dist-info/top_level.txt
neb_tasks-0.4.0.dist-info/RECORD
